structural/__init__.py
structural/_structural.so
structural/metaToolDouble
structural/structural.py
structural/test/BMID000000101155.xml
structural/test/Conservation_analysis_example.xml
structural/test/__init__.py
structural/test/elementaryModeExampleForPaper.py
structural/test/testElementaryModesUsingAntimony.py
structural/test/testElementaryModesUsingSBML.py
structural/test/testLibStructuralSBML.py
structural/test/testLibStructuralTellurium.py
structural/test/testModel1.xml
structural/test/testModel10.xml
structural/test/testModel11.xml
structural/test/testModel12.xml
structural/test/testModel13.xml
structural/test/testModel14.xml
structural/test/testModel15.xml
structural/test/testModel16.xml
structural/test/testModel17.xml
structural/test/testModel18.xml
structural/test/testModel19.xml
structural/test/testModel2.xml
structural/test/testModel20.xml
structural/test/testModel21.xml
structural/test/testModel22.xml
structural/test/testModel23.xml
structural/test/testModel24.xml
structural/test/testModel25.xml
structural/test/testModel26.xml
structural/test/testModel27.xml
structural/test/testModel28.xml
structural/test/testModel29.xml
structural/test/testModel3.xml
structural/test/testModel30.xml
structural/test/testModel31.xml
structural/test/testModel4.xml
structural/test/testModel5.xml
structural/test/testModel6.xml
structural/test/testModel7.xml
structural/test/testModel8.xml
structural/test/testModel9.xml
structural-3.1.1.dist-info/DESCRIPTION.rst
structural-3.1.1.dist-info/METADATA
structural-3.1.1.dist-info/RECORD
structural-3.1.1.dist-info/WHEEL
structural-3.1.1.dist-info/metadata.json
structural-3.1.1.dist-info/top_level.txt
