Metadata-Version: 2.0
Name: structural
Version: 3.1.1
Summary: A module for a wide variety of methods that permit access to the constraint information in the stoichiometry matrix.
Home-page: https://github.com/sys-bio/Libstructural
Author: Herbert M. Sauro and Frank T. Bergmann 
Author-email: hsauro@uw.edu
License: BSD
Keywords: systems biology
Platform: UNKNOWN
Classifier: Development Status :: 3 - Alpha
Classifier: Intended Audience :: Developers
Classifier: License :: OSI Approved :: BSD License
Classifier: Programming Language :: Python :: 2
Classifier: Programming Language :: Python :: 2.6
Classifier: Programming Language :: Python :: 2.7
Classifier: Programming Language :: Python :: 3
Classifier: Programming Language :: Python :: 3.6
